W13SCAN/__init__.py
W13SCAN/cli.py
W13SCAN/config.py
W13SCAN/api/__init__.py
W13SCAN/certs/__init__.py
W13SCAN/certs/ca.crt
W13SCAN/certs/ca.pem
W13SCAN/data/__init__.py
W13SCAN/data/wappalyzer.json
W13SCAN/lib/__init__.py
W13SCAN/lib/baseproxy.py
W13SCAN/lib/cmdparse.py
W13SCAN/lib/common.py
W13SCAN/lib/const.py
W13SCAN/lib/controller.py
W13SCAN/lib/data.py
W13SCAN/lib/datatype.py
W13SCAN/lib/loader.py
W13SCAN/lib/log.py
W13SCAN/lib/option.py
W13SCAN/lib/output.py
W13SCAN/lib/plugins.py
W13SCAN/lib/spiderset.py
W13SCAN/lib/wappanalyzer.py
W13SCAN/lib/helper/__init__.py
W13SCAN/lib/helper/diifpage.py
W13SCAN/lib/helper/helper_sqli.py
W13SCAN/lib/helper/phpinfo_helper.py
W13SCAN/lib/helper/sensitive_info.py
W13SCAN/plugins/__init__.py
W13SCAN/plugins/loader.py
W13SCAN/plugins/PerFile/__init__.py
W13SCAN/plugins/PerFile/analyze_parameter.py
W13SCAN/plugins/PerFile/command_asp_code.py
W13SCAN/plugins/PerFile/command_php_code.py
W13SCAN/plugins/PerFile/command_system.py
W13SCAN/plugins/PerFile/cookie.py
W13SCAN/plugins/PerFile/cors.py
W13SCAN/plugins/PerFile/crlf.py
W13SCAN/plugins/PerFile/directory_traversal.py
W13SCAN/plugins/PerFile/expression_language_injection.py
W13SCAN/plugins/PerFile/js_sensitive_content.py
W13SCAN/plugins/PerFile/jsonp.py
W13SCAN/plugins/PerFile/normal_page.py
W13SCAN/plugins/PerFile/php_real_path.py
W13SCAN/plugins/PerFile/redirect.py
W13SCAN/plugins/PerFile/sql_inject_bool.py
W13SCAN/plugins/PerFile/sql_inject_error.py
W13SCAN/plugins/PerFile/sql_inject_time.py
W13SCAN/plugins/PerFile/struts2_003.py
W13SCAN/plugins/PerFile/struts2_005.py
W13SCAN/plugins/PerFile/struts2_008.py
W13SCAN/plugins/PerFile/struts2_009.py
W13SCAN/plugins/PerFile/struts2_013.py
W13SCAN/plugins/PerFile/struts2_015.py
W13SCAN/plugins/PerFile/struts2_016.py
W13SCAN/plugins/PerFile/struts2_019.py
W13SCAN/plugins/PerFile/struts2_032.py
W13SCAN/plugins/PerFile/struts2_033.py
W13SCAN/plugins/PerFile/struts2_037.py
W13SCAN/plugins/PerFile/struts2_045.py
w13scan-0.9.17.dist-info/LICENSE
w13scan-0.9.17.dist-info/METADATA
w13scan-0.9.17.dist-info/WHEEL
w13scan-0.9.17.dist-info/entry_points.txt
w13scan-0.9.17.dist-info/top_level.txt
w13scan-0.9.17.dist-info/RECORD
