Metadata-Version: 2.1
Name: w13scan
Version: 0.9.17
Summary: Passive Web Security Scanner
Home-page: https://github.com/boy-hack/w13scan.git
Author: boy-hack
Author-email: master@hacking8.com
License: UNKNOWN
Keywords: scanner,w13scan
Platform: any
Classifier: Topic :: Security
Classifier: Programming Language :: Python :: 3
Classifier: License :: OSI Approved :: GNU General Public License v2 (GPLv2)
Requires-Python: >=3.4
Requires-Dist: asn1crypto (==0.24.0)
Requires-Dist: certifi (==2019.6.16)
Requires-Dist: cffi (==1.12.3)
Requires-Dist: chardet (==3.0.4)
Requires-Dist: colorama (==0.4.1)
Requires-Dist: cryptography (==2.7)
Requires-Dist: idna (==2.8)
Requires-Dist: pycparser (==2.19)
Requires-Dist: pyOpenSSL (==18.0.0)
Requires-Dist: requests (==2.22.0)
Requires-Dist: six (==1.12.0)
Requires-Dist: tld (==0.9.3)
Requires-Dist: urllib3 (==1.25.3)
